{
  "genesis_time": "2019-10-30T17:11:44.862528854Z",
  "chain_id": "OneLedger-7599",
  "consensus_params": {
    "block": {
      "max_bytes": "22020096",
      "max_gas": "-1",
      "time_iota_ms": "1000"
    },
    "evidence": {
      "max_age": "100000"
    },
    "validator": {
      "pub_key_types": [
        "ed25519"
      ]
    }
  },
  "validators": [
    {
      "address": "1782EAFD0DD568F6C330DC2F74DC47F8D64E2CAF",
      "pub_key": {
        "type": "tendermint/PubKeyEd25519",
        "value": "WTDgrnyGeBdUguYW6ZOonuYWCcTLdPKrcqWHN2yknF0="
      },
      "power": "1",
      "name": "0"
    },
    {
      "address": "BFA47D99738B610EC140B5FD82C9974B13E8534A",
      "pub_key": {
        "type": "tendermint/PubKeyEd25519",
        "value": "/9z5nvMATdhX/ihoCULMvaCcmBst0cC5KLPwRREFmBo="
      },
      "power": "1",
      "name": "1"
    },
    {
      "address": "EE8BC90E2D3D295B97EDE002C766DA4F80AD52F1",
      "pub_key": {
        "type": "tendermint/PubKeyEd25519",
        "value": "7bFXnGPf5CvbeHti7qYUooCkhvAR00sSMJVEUmgwp7A="
      },
      "power": "1",
      "name": "2"
    },
    {
      "address": "CDA82C79B0D370079EDB59BDEC6E7FF699E867E3",
      "pub_key": {
        "type": "tendermint/PubKeyEd25519",
        "value": "2UVPBIE4PPzlvsneoWRSwElj68vGIzDnlE0r5vAy9q8="
      },
      "power": "1",
      "name": "3"
    }
  ],
  "app_hash": "",
  "app_state": {
    "currencies": [
      {
        "id": 0,
        "name": "OLT",
        "chain": 0,
        "decimal": 18,
        "unit": "nue"
      },
      {
        "id": 1,
        "name": "VT",
        "chain": 0,
        "decimal": 0,
        "unit": "vt"
      }
    ],
    "feeOption": {
      "feeCurrency": {
        "id": 0,
        "name": "OLT",
        "chain": 0,
        "decimal": 18,
        "unit": "nue"
      },
      "minFeeDecimal": 9
    },
    "balances": [
      {
        "address": "0x6b3fcf2b8fb1e26e900158c98747a909d61e5669",
        "currency": "VT",
        "amount": "100"
      },
      {
        "address": "0x38b2f72a2fb9d20f9276c422bbf1026081e7112c",
        "currency": "VT",
        "amount": "100"
      },
      {
        "address": "0x7ef19f7ce1e7b802d1347aed0fa02461ebbcdb4a",
        "currency": "VT",
        "amount": "100"
      },
      {
        "address": "0xa825eb239d6273be5e83e0bff62b2f3a171ef2c3",
        "currency": "VT",
        "amount": "100"
      },
      {
        "address": "0x6b3fcf2b8fb1e26e900158c98747a909d61e5669",
        "currency": "OLT",
        "amount": "250000000000000000000000000"
      },
      {
        "address": "0x38b2f72a2fb9d20f9276c422bbf1026081e7112c",
        "currency": "OLT",
        "amount": "250000000000000000000000000"
      },
      {
        "address": "0x7ef19f7ce1e7b802d1347aed0fa02461ebbcdb4a",
        "currency": "OLT",
        "amount": "250000000000000000000000000"
      },
      {
        "address": "0xa825eb239d6273be5e83e0bff62b2f3a171ef2c3",
        "currency": "OLT",
        "amount": "250000000000000000000000000"
      }
    ],
    "staking": [
      {
        "ValidatorAddress": "0x1782eafd0dd568f6c330dc2f74dc47f8d64e2caf",
        "StakeAddress": "0x6b3fcf2b8fb1e26e900158c98747a909d61e5669",
        "Pubkey": {
          "keyType": "ed25519",
          "data": "WTDgrnyGeBdUguYW6ZOonuYWCcTLdPKrcqWHN2yknF0="
        },
        "ECDSAPubKey": {
          "keyType": "secp256k1",
          "data": "61rphyEDR7Im7/ydjIwh88TdQNvqJALnJn8b7M0qWuJHs31jcjQ="
        },
        "Name": "0",
        "Amount": "1"
      },
      {
        "ValidatorAddress": "0xbfa47d99738b610ec140b5fd82c9974b13e8534a",
        "StakeAddress": "0x38b2f72a2fb9d20f9276c422bbf1026081e7112c",
        "Pubkey": {
          "keyType": "ed25519",
          "data": "/9z5nvMATdhX/ihoCULMvaCcmBst0cC5KLPwRREFmBo="
        },
        "ECDSAPubKey": {
          "keyType": "secp256k1",
          "data": "61rphyEDPmdwyy02a3fCTZYimKlCwGSqd6Z014L5jspEwTokNB8="
        },
        "Name": "1",
        "Amount": "1"
      },
      {
        "ValidatorAddress": "0xee8bc90e2d3d295b97ede002c766da4f80ad52f1",
        "StakeAddress": "0x7ef19f7ce1e7b802d1347aed0fa02461ebbcdb4a",
        "Pubkey": {
          "keyType": "ed25519",
          "data": "7bFXnGPf5CvbeHti7qYUooCkhvAR00sSMJVEUmgwp7A="
        },
        "ECDSAPubKey": {
          "keyType": "secp256k1",
          "data": "61rphyEDebLMk+b7GSkqpNjtvsipMiAeMT5ulxIUfwosGWtVhug="
        },
        "Name": "2",
        "Amount": "1"
      },
      {
        "ValidatorAddress": "0xcda82c79b0d370079edb59bdec6e7ff699e867e3",
        "StakeAddress": "0xa825eb239d6273be5e83e0bff62b2f3a171ef2c3",
        "Pubkey": {
          "keyType": "ed25519",
          "data": "2UVPBIE4PPzlvsneoWRSwElj68vGIzDnlE0r5vAy9q8="
        },
        "ECDSAPubKey": {
          "keyType": "secp256k1",
          "data": "61rphyED06zonIUh320t6AAXR8GEwS4I4XigO/RFwYSVVAEXo/c="
        },
        "Name": "3",
        "Amount": "1"
      }
    ],
    "domains": [],
    "fees": []
  }
}